{
   "predictions" : [
      {
         "description" : "Deventer, The Netherlands",
         "id" : "843538b8f2308056edb1a8d11d0bed0dcec01087",
         "matched_substrings" : [
            {
               "length" : 8,
               "offset" : 0
            }
         ],
         "place_id" : "CkQxAAAAaSPEKxAHaEMEfXqOiOzsG2eXA-nEhj9moN1WdLGcU5vbbH4xRsyMqxOrWxDOgZZK3TOc2pRtBwizFZsLfPvymxIQwYbT3eljgi1z_OqWP4V5ThoUFP8oWfCjySHtTp8db0USQbLj9Ww",
         "terms" : [
            {
               "offset" : 0,
               "value" : "Deventer"
            },
            {
               "offset" : 10,
               "value" : "The Netherlands"
            }
         ],
         "types" : [ "locality", "political", "geocode" ]
      },
      {
         "description" : "Deventer, MO, United States",
         "id" : "16066b8ed6f7d40d5c279c13f1b14a68fd133595",
         "matched_substrings" : [
            {
               "length" : 8,
               "offset" : 0
            }
         ],
         "place_id" : "CkQzAAAAO82_HQKci1tiFUdeyxiODVQDyb00SKo6la1sz0YFbACBW8ruj33y3PLUU1IC6I4VOgg4R_qqUtgNsCJPQ6OKRxIQCQxUH8DghtFTQdV0zMa9vxoUOYfsRL4UFY73zAY0PSHMceDxiKw",
         "terms" : [
            {
               "offset" : 0,
               "value" : "Deventer"
            },
            {
               "offset" : 10,
               "value" : "MO"
            },
            {
               "offset" : 14,
               "value" : "United States"
            }
         ],
         "types" : [ "locality", "political", "geocode" ]
      },
      {
         "description" : "Deventer Crescent, Camberwell, United Kingdom",
         "id" : "7dd097d82375eb159b244aba1a299482c73a3c57",
         "matched_substrings" : [
            {
               "length" : 8,
               "offset" : 0
            }
         ],
         "place_id" : "ClRFAAAAPM3xLL2EH13DGrXfCsVJKvL8sSJWKs20q7l5f2xW9hzc6zJmaTeCWVlgedRRskKr5r39lgtfKFjJpwqcE_zk7TaDlgKBtopEVHn24ZbR6vkSENl5laX5pxPoEFPePia9ivIaFBdGtxagSTujvSqjcfkLwj-R-Fu2",
         "terms" : [
            {
               "offset" : 0,
               "value" : "Deventer Crescent"
            },
            {
               "offset" : 19,
               "value" : "Camberwell"
            },
            {
               "offset" : 31,
               "value" : "United Kingdom"
            }
         ],
         "types" : [ "route", "geocode" ]
      },
      {
         "description" : "Deventer Drive, La Verne, CA, United States",
         "id" : "95647229cf020ae34b914289ac38684b68f558dd",
         "matched_substrings" : [
            {
               "length" : 8,
               "offset" : 0
            }
         ],
         "place_id" : "ClRDAAAAkZIQE7lUhLkCBWcwUrWPejMEl2YF4_wDA3n6kZHEE-W6rpU-heR0rtd3Xtq_Fh3bjGp8BlMAcEEwCEdEznB41G2ooVWu8xh5AU8wGSRt2VkSENtalRhpG41HWU_1L1EdV4EaFKVKYYk4BPZH2UYnmsKTZ11cFBtp",
         "terms" : [
            {
               "offset" : 0,
               "value" : "Deventer Drive"
            },
            {
               "offset" : 16,
               "value" : "La Verne"
            },
            {
               "offset" : 26,
               "value" : "CA"
            },
            {
               "offset" : 30,
               "value" : "United States"
            }
         ],
         "types" : [ "route", "geocode" ]
      },
      {
         "description" : "VVV Deventer, Pikeursbaan, Deventer, The Netherlands",
         "id" : "0b00e188d43b6d5da83552aa7154a73270279376",
         "matched_substrings" : [
            {
               "length" : 8,
               "offset" : 4
            }
         ],
         "place_id" : "CmRWAAAA7JnAOFtqLCAaXshQhWqjBC6hUZ1DP-6OGUK0lmt-gT7cxP_RRrlXjIzWgK2rUwcJFcUaibEuiNbj6jReqyiHMrv_VMcMrB3xC2PLMDWFih19nDTwPfU-pULL61yYWjcDEhClXmEG1s7jrEBPFFN76J8xGhStBuODuC9mCXAX5XoGpYHg2OY-sA",
         "terms" : [
            {
               "offset" : 0,
               "value" : "VVV Deventer"
            },
            {
               "offset" : 14,
               "value" : "Pikeursbaan"
            },
            {
               "offset" : 27,
               "value" : "Deventer"
            },
            {
               "offset" : 37,
               "value" : "The Netherlands"
            }
         ],
         "types" : [ "establishment" ]
      }
   ],
   "status" : "OK"
}
